mccode_to_kafka/__init__.py
mccode_to_kafka/datfile.py
mccode_to_kafka/histogram.py
mccode_to_kafka/sender.py
mccode_to_kafka/utils.py
mccode_to_kafka/writer.py
mccode_to_kafka-0.5.0.dist-info/METADATA
mccode_to_kafka-0.5.0.dist-info/WHEEL
mccode_to_kafka-0.5.0.dist-info/entry_points.txt
mccode_to_kafka-0.5.0.dist-info/top_level.txt
mccode_to_kafka-0.5.0.dist-info/RECORD
