Metadata-Version: 2.4
Name: mccode-to-kafka
Version: 0.5.0
Summary: Send McCode generated histograms to a Kafka server as da00 messages
Author-email: Gregory Tucker <gregory.tucker@ess.eu>
Project-URL: Homepage, https://github.com/g5t/mccode-to-kafka
Classifier: License :: OSI Approved :: BSD License
Requires-Dist: ess-streaming-data-types>=0.26.1
Requires-Dist: confluent-kafka>=2.3.0
Requires-Dist: numpy
Requires-Dist: importlib_metadata; python_version < "3.8"
Provides-Extra: test
Requires-Dist: pytest; extra == "test"
Requires-Dist: mock; extra == "test"
Requires-Dist: flake8-pyproject; extra == "test"
Requires-Dist: file-writer-control; extra == "test"
Requires-Dist: python-on-whales; extra == "test"
Requires-Dist: h5py; extra == "test"
